answer.py
universal_answer_package_tutorial-0.0.1.dist-info/LICENSE.txt
universal_answer_package_tutorial-0.0.1.dist-info/METADATA
universal_answer_package_tutorial-0.0.1.dist-info/WHEEL
universal_answer_package_tutorial-0.0.1.dist-info/top_level.txt
universal_answer_package_tutorial-0.0.1.dist-info/RECORD
