Metadata-Version: 2.1
Name: universal-answer-package-tutorial
Version: 0.0.1
Summary: Universal tool to determine the answer.
Home-page: https://github.com/MDornacher/universal-answer
Author: Manuel Dornacher
Author-email: manuel.dornacher@gmail.com
License: MIT License
Platform: UNKNOWN
Classifier: Programming Language :: Python :: 3
Classifier: Programming Language :: Python :: 3.7
Classifier: Programming Language :: Python :: 3.8
Classifier: Programming Language :: Python :: 3.9
Classifier: License :: OSI Approved :: MIT License
Classifier: Operating System :: OS Independent
Classifier: Topic :: Education :: Testing
License-File: LICENSE.txt
Requires-Dist: tqdm (~=4.62)
Provides-Extra: dev
Requires-Dist: pytest (>=6.2) ; extra == 'dev'
Requires-Dist: check-manifest ; extra == 'dev'
